notion_to_json/__init__.py
notion_to_json/__main__.py
notion_to_json/cli.py
notion_to_json/client.py
notion_to_json/exporter.py
notion_to_json/logging.py
notion_to_json/models.py
notion_to_json-1.1.0.dist-info/METADATA
notion_to_json-1.1.0.dist-info/WHEEL
notion_to_json-1.1.0.dist-info/entry_points.txt
notion_to_json-1.1.0.dist-info/licenses/LICENSE
notion_to_json-1.1.0.dist-info/RECORD
