Metadata-Version: 2.4
Name: notion-to-json
Version: 1.1.0
Summary: Export Notion pages and databases to JSON with filtering and advanced options
Project-URL: Homepage, https://github.com/jonatkinson/notion-to-json
Project-URL: Repository, https://github.com/jonatkinson/notion-to-json
Project-URL: Issues, https://github.com/jonatkinson/notion-to-json/issues
Author-email: Jon Atkinson <jon@jonatkinson.co.uk>
Maintainer-email: Jon Atkinson <jon@jonatkinson.co.uk>
License: MIT
License-File: LICENSE
Keywords: api,backup,export,json,notion
Classifier: Development Status :: 4 - Beta
Classifier: Environment :: Console
Classifier: Intended Audience :: Developers
Classifier: Intended Audience :: End Users/Desktop
Classifier: License :: OSI Approved :: MIT License
Classifier: Operating System :: OS Independent
Classifier: Programming Language :: Python :: 3
Classifier: Programming Language :: Python :: 3.13
Classifier: Topic :: Office/Business
Classifier: Topic :: Utilities
Requires-Python: >=3.13
Requires-Dist: click>=8.1.7
Requires-Dist: httpx>=0.27.0
Requires-Dist: python-dotenv>=1.0.0
Requires-Dist: rich>=13.7.0
